pprodigal/__init__.py
pprodigal/pprodigal.py
pprodigal-1.0.1.dist-info/LICENSE
pprodigal-1.0.1.dist-info/METADATA
pprodigal-1.0.1.dist-info/WHEEL
pprodigal-1.0.1.dist-info/entry_points.txt
pprodigal-1.0.1.dist-info/top_level.txt
pprodigal-1.0.1.dist-info/RECORD
