Metadata-Version: 2.1
Name: pprodigal
Version: 1.0.1
Summary: PProdigal: Parallelized gene prediction based on Prodigal.
Home-page: https://github.com/sjaenick/pprodigal
Author: Sebastian Jaenicke
Author-email: sebastian.jaenicke@computational.bio.uni-giessen.de
License: MIT
Project-URL: Bug Reports, https://github.com/sjaenick/pprodigal/issues
Project-URL: Source, https://github.com/sjaenick/pprodigal
Keywords: bioinformatics,gene prediction
Platform: UNKNOWN
Classifier: Operating System :: POSIX :: Linux
Classifier: Programming Language :: Python :: 3 :: Only
Classifier: Development Status :: 5 - Production/Stable
Classifier: License :: OSI Approved :: MIT License
Classifier: Topic :: Scientific/Engineering :: Bio-Informatics
Classifier: Environment :: Console
Classifier: Intended Audience :: Science/Research
Classifier: Natural Language :: English
Requires-Python: >=3.0
License-File: LICENSE
